{"id":"c7c23f4f-909d-1c9c-e9e9-87add04e6b29","name":"Collect-Offer","timestamp":1614410758487,"requests":[{"collectionId":"c7c23f4f-909d-1c9c-e9e9-87add04e6b29","id":"16aca7ea-3d6f-5e61-0f72-f33e4d2e936e","name":"XML all offers (default pagesize 3)","description":"","url":"http://localhost:8080/collect/offer","method":"GET","headers":"Accept: application/xml\nAuthorization: Basic dXNlcjpwYXNzd29yZA==\n","data":"{\n        \"name\": \"NEWYEAR2021\",\n  \t\t\"validFrom\":\"2021-01-20\",\n  \t\t\"validTill\": \"2021-06-20\",\n  \t\t\"location\":\"Delhi\"\n}","dataMode":"raw","timestamp":0,"version":2,"time":1614431450168},{"collectionId":"c7c23f4f-909d-1c9c-e9e9-87add04e6b29","id":"4a405814-9269-7282-3298-44b8692e3231","name":"offer pagination page2 size3","description":"","url":"http://localhost:8080/collect/offer?page=2","method":"GET","headers":"Accept: application/json\nAuthorization: Basic dXNlcjpwYXNzd29yZA==\n","data":"[{\n        \"name\": \"NEWYEAR2021\",\n  \t\t\"validFrom\":\"2021-01-20\",\n  \t\t\"validTill\": \"2021-06-20\",\n  \t\t\"location\":\"Delhi\"\n},\n {\n        \"name\": \"HAPPY2021\",\n  \t\t\"validFrom\":\"2021-01-20\",\n  \t\t\"validTill\": \"2021-06-20\",\n  \t\t\"location\":\"Mumbai\"\n},\n {\n        \"name\": \"NEWYEAR2020\",\n  \t\t\"validFrom\":\"2020-01-20\",\n  \t\t\"validTill\": \"2020-06-20\",\n  \t\t\"location\":\"Delhi\"\n},\n {\n        \"name\": \"HAPPY2020\",\n  \t\t\"validFrom\":\"2021-01-20\",\n  \t\t\"validTill\": \"2021-06-20\",\n  \t\t\"location\":\"Mumbai\"\n},\n {\n        \"name\": \"FLAT50\",\n  \t\t\"validFrom\":\"2021-01-20\",\n  \t\t\"validTill\": \"2021-06-20\",\n  \t\t\"location\":\"Karnataka\"\n},\n {\n        \"name\": \"FLAT20\",\n  \t\t\"validFrom\":\"2021-01-20\",\n  \t\t\"validTill\": \"2021-06-20\",\n  \t\t\"location\":\"Karnataka\"\n},\n{\n        \"name\": \"FLAT30OFF\",\n  \t\t\"validFrom\":\"2021-01-20\",\n  \t\t\"validTill\": \"2021-06-20\",\n  \t\t\"location\":\"Karnataka\"\n}]","dataMode":"raw","timestamp":0,"responses":[],"version":2},{"collectionId":"c7c23f4f-909d-1c9c-e9e9-87add04e6b29","id":"8401f51c-75cf-095a-d00b-1a4d96c79f45","name":"create offer","description":"","url":"http://localhost:8080/collect/offer/","method":"POST","headers":"Content-Type: application/json\nAuthorization: Basic dXNlcjpwYXNzd29yZA==\n","data":"{\n        \"name\": \"NEWYEAR2021\",\n  \t\t\"validFrom\":\"2021-01-20\",\n  \t\t\"validTill\": \"2021-06-20\",\n  \t\t\"location\":\"Delhi\"\n}","dataMode":"raw","timestamp":0,"version":2,"time":1614431440369},{"collectionId":"c7c23f4f-909d-1c9c-e9e9-87add04e6b29","id":"8aaf8cc6-fe3a-173d-40a2-dfdb9d239a89","name":"XML offers pagination and search by name NEWYEAR2021","description":"","url":"http://localhost:8080/collect/offer?page=0&size=2&name=NEWYEAR2021","method":"GET","headers":"Accept: application/xml\nAuthorization: Basic dXNlcjpwYXNzd29yZA==\n","data":"[{\n        \"name\": \"NEWYEAR2021\",\n  \t\t\"validFrom\":\"2021-01-20\",\n  \t\t\"validTill\": \"2021-06-20\",\n  \t\t\"location\":\"Delhi\"\n},\n {\n        \"name\": \"HAPPY2021\",\n  \t\t\"validFrom\":\"2021-01-20\",\n  \t\t\"validTill\": \"2021-06-20\",\n  \t\t\"location\":\"Mumbai\"\n},\n {\n        \"name\": \"NEWYEAR2020\",\n  \t\t\"validFrom\":\"2020-01-20\",\n  \t\t\"validTill\": \"2020-06-20\",\n  \t\t\"location\":\"Delhi\"\n},\n {\n        \"name\": \"HAPPY2020\",\n  \t\t\"validFrom\":\"2021-01-20\",\n  \t\t\"validTill\": \"2021-06-20\",\n  \t\t\"location\":\"Mumbai\"\n},\n {\n        \"name\": \"FLAT50\",\n  \t\t\"validFrom\":\"2021-01-20\",\n  \t\t\"validTill\": \"2021-06-20\",\n  \t\t\"location\":\"Karnataka\"\n},\n {\n        \"name\": \"FLAT20\",\n  \t\t\"validFrom\":\"2021-01-20\",\n  \t\t\"validTill\": \"2021-06-20\",\n  \t\t\"location\":\"Karnataka\"\n},\n{\n        \"name\": \"FLAT30OFF\",\n  \t\t\"validFrom\":\"2021-01-20\",\n  \t\t\"validTill\": \"2021-06-20\",\n  \t\t\"location\":\"Karnataka\"\n}]","dataMode":"raw","timestamp":0,"responses":[],"version":2},{"collectionId":"c7c23f4f-909d-1c9c-e9e9-87add04e6b29","id":"a192bf67-534c-d9f2-a3d4-1b0d9b252c61","name":"offer pagination size 10","description":"","url":"http://localhost:8080/collect/offer?size=10","method":"GET","headers":"Accept: application/json\nAuthorization: Basic dXNlcjpwYXNzd29yZA==\n","data":"[{\n        \"name\": \"NEWYEAR2021\",\n  \t\t\"validFrom\":\"2021-01-20\",\n  \t\t\"validTill\": \"2021-06-20\",\n  \t\t\"location\":\"Delhi\"\n},\n {\n        \"name\": \"HAPPY2021\",\n  \t\t\"validFrom\":\"2021-01-20\",\n  \t\t\"validTill\": \"2021-06-20\",\n  \t\t\"location\":\"Mumbai\"\n},\n {\n        \"name\": \"NEWYEAR2020\",\n  \t\t\"validFrom\":\"2020-01-20\",\n  \t\t\"validTill\": \"2020-06-20\",\n  \t\t\"location\":\"Delhi\"\n},\n {\n        \"name\": \"HAPPY2020\",\n  \t\t\"validFrom\":\"2021-01-20\",\n  \t\t\"validTill\": \"2021-06-20\",\n  \t\t\"location\":\"Mumbai\"\n},\n {\n        \"name\": \"FLAT50\",\n  \t\t\"validFrom\":\"2021-01-20\",\n  \t\t\"validTill\": \"2021-06-20\",\n  \t\t\"location\":\"Karnataka\"\n},\n {\n        \"name\": \"FLAT20\",\n  \t\t\"validFrom\":\"2021-01-20\",\n  \t\t\"validTill\": \"2021-06-20\",\n  \t\t\"location\":\"Karnataka\"\n},\n{\n        \"name\": \"FLAT30OFF\",\n  \t\t\"validFrom\":\"2021-01-20\",\n  \t\t\"validTill\": \"2021-06-20\",\n  \t\t\"location\":\"Karnataka\"\n}]","dataMode":"raw","timestamp":0,"responses":[],"version":2},{"collectionId":"c7c23f4f-909d-1c9c-e9e9-87add04e6b29","id":"ae0619a1-56e6-faa5-0bac-943215310716","name":"create multiple offer","description":"","url":"http://localhost:8080/collect/offers","method":"POST","headers":"Content-Type: application/json\nAuthorization: Basic dXNlcjpwYXNzd29yZA==\n","data":"[{\n        \"name\": \"NEWYEAR2021\",\n  \t\t\"validFrom\":\"2021-01-20\",\n  \t\t\"validTill\": \"2021-06-20\",\n  \t\t\"location\":\"Delhi\"\n},\n {\n        \"name\": \"HAPPY2021\",\n  \t\t\"validFrom\":\"2021-01-20\",\n  \t\t\"validTill\": \"2021-06-20\",\n  \t\t\"location\":\"Mumbai\"\n},\n {\n        \"name\": \"NEWYEAR2020\",\n  \t\t\"validFrom\":\"2020-01-20\",\n  \t\t\"validTill\": \"2020-06-20\",\n  \t\t\"location\":\"Delhi\"\n},\n {\n        \"name\": \"HAPPY2020\",\n  \t\t\"validFrom\":\"2021-01-20\",\n  \t\t\"validTill\": \"2021-06-20\",\n  \t\t\"location\":\"Mumbai\"\n},\n {\n        \"name\": \"FLAT50\",\n  \t\t\"validFrom\":\"2021-01-20\",\n  \t\t\"validTill\": \"2021-06-20\",\n  \t\t\"location\":\"Karnataka\"\n},\n {\n        \"name\": \"FLAT20\",\n  \t\t\"validFrom\":\"2021-01-20\",\n  \t\t\"validTill\": \"2021-06-20\",\n  \t\t\"location\":\"Karnataka\"\n},\n{\n        \"name\": \"FLAT30OFF\",\n  \t\t\"validFrom\":\"2021-01-20\",\n  \t\t\"validTill\": \"2021-06-20\",\n  \t\t\"location\":\"Karnataka\"\n}]","dataMode":"raw","timestamp":0,"responses":[],"version":2},{"collectionId":"c7c23f4f-909d-1c9c-e9e9-87add04e6b29","id":"e9f703fb-f6c2-a30a-01c6-d8854d18ae04","name":"offers pagination and search by name NEWYEAR2021","description":"","url":"http://localhost:8080/collect/offer?page=0&size=2&name=NEWYEAR2021","method":"GET","headers":"Accept: application/json\nAuthorization: Basic dXNlcjpwYXNzd29yZA==\n","data":"{\n        \"name\": \"NEWYEAR2021111\",\n  \t\t\"validFrom\":\"2021-01-20\",\n  \t\t\"validTill\": \"2021-06-20\",\n  \t\t\"location\":\"Delhi\"\n}","dataMode":"raw","timestamp":0,"responses":[],"version":2},{"collectionId":"c7c23f4f-909d-1c9c-e9e9-87add04e6b29","id":"f1dcd734-57cb-8176-f397-3748d7e72560","name":"all offers (default pagesize 3)","description":"","url":"http://localhost:8080/collect/offer","method":"GET","headers":"Accept: application/json\nAuthorization: Basic dXNlcjpwYXNzd29yZA==\n","data":"{\n        \"name\": \"NEWYEAR2021\",\n  \t\t\"validFrom\":\"2021-01-20\",\n  \t\t\"validTill\": \"2021-06-20\",\n  \t\t\"location\":\"Delhi\"\n}","dataMode":"raw","timestamp":0,"version":2,"time":1614431433880}]}
